search_web/__init__.py
search_web-0.1.6.dist-info/LICENSE.txt
search_web-0.1.6.dist-info/METADATA
search_web-0.1.6.dist-info/WHEEL
search_web-0.1.6.dist-info/top_level.txt
search_web-0.1.6.dist-info/RECORD
