Metadata-Version: 2.1
Name: search-web
Version: 0.1.6
Summary: This module will Help You to Search on More Than 45 Websites like Google,Youtube,etc. By Just 2 lines Of Code
Home-page: https://github.com/Ankitsinghprograms/search_web
Author: Ankit Singh
Author-email: ankitsingh300307@gmail.com
License: UNKNOWN
Platform: UNKNOWN
Classifier: Programming Language :: Python :: 3
Classifier: License :: OSI Approved :: MIT License
Classifier: Operating System :: OS Independent
Requires-Python: >=3.0
